{
  "paper_id": "apep_0453",
  "family_id": "apep_0453",
  "version": 1,
  "started_at": "2026-02-25T13:46:50.247575",
  "finished_at": "2026-02-25T14:53:55.003186",
  "total_seconds": 4024.755619,
  "phases": {
    "setup": {
      "started_at": "2026-02-25T13:46:50.247575",
      "finished_at": "2026-02-25T13:46:55.251430",
      "duration_seconds": 5.003864
    },
    "discovery": {
      "started_at": "2026-02-25T13:48:34.789823",
      "finished_at": "2026-02-25T13:57:43.919330",
      "duration_seconds": 549.129524
    },
    "ranking": {
      "started_at": "2026-02-25T13:57:43.919330",
      "finished_at": "2026-02-25T13:57:47.813039",
      "duration_seconds": 3.893718
    },
    "execution": {
      "started_at": "2026-02-25T13:57:47.813039",
      "finished_at": "2026-02-25T14:45:07.902629",
      "duration_seconds": 2840.089597
    },
    "external_review": {
      "started_at": "2026-02-25T15:04:20.347130",
      "finished_at": null,
      "duration_seconds": null
    },
    "internal_review": {
      "started_at": "2026-02-25T14:45:59.222577",
      "finished_at": "2026-02-25T14:45:59.259380",
      "duration_seconds": 0.036817
    },
    "publish": {
      "started_at": "2026-02-25T14:53:54.975916",
      "finished_at": "2026-02-25T14:53:55.003186",
      "duration_seconds": 0.027278
    }
  }
}
