{
  "iteration": 1,
  "max_iterations": 3,
  "proceed_to_phase4": true,
  "reason": "PURSUE idea found",
  "best_idea": {
    "rank": 1,
    "title": "From Workplace to Living Room \u2014 Do Indoor Smoking Bans Cultivate Anti-Smoking Norms Beyond Their Legal Reach?",
    "score": 73,
    "recommendation": "PURSUE",
    "conditions": [
      "using month-of-interview to construct full-exposure measures or dropping partial-exposure first years",
      "explicitly controlling for cigarette taxes",
      "tobacco-control funding",
      "major cessation-coverage expansions",
      "demonstrating clean pre-trends",
      "running \u201cleave-one-region-out\u201d/border-state robustness"
    ]
  },
  "timestamp": "2026-02-13T15:02:34.798280"
}