{
  "paper_dir": "output/paper_181",
  "started_at": "2026-02-06T13:35:03.896433",
  "finished_at": null,
  "phases": {
    "setup": {
      "started_at": "2026-02-06T13:35:03.896433",
      "finished_at": "2026-02-06T13:35:03.931169",
      "duration_seconds": 0.034743
    },
    "execution": {
      "started_at": "2026-02-06T13:35:03.931169",
      "finished_at": "2026-02-06T15:36:30.831023",
      "duration_seconds": 7286.89986
    },
    "internal_review": {
      "started_at": "2026-02-06T15:36:30.831023",
      "finished_at": "2026-02-06T15:36:30.863276",
      "duration_seconds": 0.032258
    },
    "external_review": {
      "started_at": "2026-02-06T15:36:30.863276",
      "finished_at": null,
      "duration_seconds": null
    }
  },
  "total_seconds": null
}
