{
  "iteration": 1,
  "max_iterations": 3,
  "proceed_to_phase4": true,
  "reason": "PURSUE idea found",
  "best_idea": {
    "rank": 1,
    "title": "Minimum Wage Increases and Teen Time Allocation: Direct and Spillover Effects",
    "score": 72,
    "recommendation": "PURSUE",
    "conditions": [
      "coding treatment by effective date using ATUS interview/diary month",
      "pre-trend/event-study diagnostics by cohort",
      "a clear plan for dilution/power\u2014especially for spillovers",
      "explicit controls/robustness for bundled state policy changes"
    ]
  },
  "timestamp": "2026-01-27T08:37:12.971829"
}