{
  "iteration": 1,
  "max_iterations": 3,
  "proceed_to_phase4": true,
  "reason": "PURSUE idea found",
  "best_idea": {
    "rank": 1,
    "title": "The Green Rush at State Borders: Difference-in-Discontinuities for Marijuana Effects on Employment (Idea 2)",
    "score": 69,
    "recommendation": "PURSUE",
    "conditions": [
      "extending pre-period to \u22655 years",
      "expanding treated states/borders to raise treated border clusters",
      "explicitly modeling anticipation using event time around election",
      "retail opening"
    ]
  },
  "timestamp": "2026-02-04T00:07:39.978233"
}