{
  "paper_id": "apep_0469",
  "family_id": "apep_0469",
  "version": 2,
  "started_at": "2026-02-27T14:00:00.000000",
  "phases": {
    "setup": {
      "started_at": "2026-02-27T14:00:00.000000",
      "finished_at": "2026-02-27T14:05:00.000000",
      "duration_seconds": 300
    },
    "discovery": {
      "started_at": "2026-02-27T14:05:00.000000",
      "finished_at": "2026-02-27T14:10:00.000000",
      "duration_seconds": 300
    },
    "ranking": {
      "started_at": "2026-02-27T14:10:00.000000",
      "finished_at": "2026-02-27T14:15:00.000000",
      "duration_seconds": 300
    },
    "execution": {
      "started_at": "2026-02-27T14:15:00.000000",
      "finished_at": "2026-02-27T20:00:00.000000",
      "duration_seconds": 20700
    },
    "external_review": {
      "started_at": "2026-02-27T16:44:47.258568",
      "finished_at": null,
      "duration_seconds": null
    },
    "internal_review": {
      "started_at": "2026-02-27T15:31:35.355827",
      "finished_at": "2026-02-27T15:35:00.000000",
      "duration_seconds": 205
    },
    "publish": {
      "started_at": "2026-02-27T16:12:58.606643",
      "finished_at": "2026-02-27T16:12:58.640087",
      "duration_seconds": 0.033451
    }
  },
  "finished_at": "2026-02-27T16:12:58.640087",
  "total_seconds": 7978.640094
}
