{
  "iteration": 1,
  "max_iterations": 3,
  "proceed_to_phase4": true,
  "reason": "PURSUE idea found",
  "best_idea": {
    "rank": 1,
    "title": "The Elasticity of Medicaid's Safety Net \u2014 Market Responses to Provider Fraud Exclusions",
    "score": 74,
    "recommendation": "PURSUE",
    "conditions": [
      "extending pre-period or restricting to later exclusions",
      "defining outcomes net-of-excluded-provider",
      "focusing on high-share providers / tighter markets",
      "explicit tests for anticipatory effects",
      "enforcement-wave confounding"
    ]
  },
  "timestamp": "2026-02-18T11:20:05.945232"
}